odoo/addons/server_action_mass_edit_onchange/README.rst
odoo/addons/server_action_mass_edit_onchange/__init__.py
odoo/addons/server_action_mass_edit_onchange/__manifest__.py
odoo/addons/server_action_mass_edit_onchange/i18n/it.po
odoo/addons/server_action_mass_edit_onchange/i18n/server_action_mass_edit_onchange.pot
odoo/addons/server_action_mass_edit_onchange/models/__init__.py
odoo/addons/server_action_mass_edit_onchange/models/ir_actions_server.py
odoo/addons/server_action_mass_edit_onchange/models/ir_actions_server_mass_edit_line.py
odoo/addons/server_action_mass_edit_onchange/readme/CONTRIBUTORS.md
odoo/addons/server_action_mass_edit_onchange/readme/DESCRIPTION.md
odoo/addons/server_action_mass_edit_onchange/static/description/icon.png
odoo/addons/server_action_mass_edit_onchange/static/description/index.html
odoo/addons/server_action_mass_edit_onchange/tests/__init__.py
odoo/addons/server_action_mass_edit_onchange/tests/test_mass_editing.py
odoo/addons/server_action_mass_edit_onchange/views/ir_actions_server.xml
odoo/addons/server_action_mass_edit_onchange/wizard/__init__.py
odoo/addons/server_action_mass_edit_onchange/wizard/mass_editing_wizard.py
odoo_addon_server_action_mass_edit_onchange-18.0.1.1.1.dist-info/METADATA
odoo_addon_server_action_mass_edit_onchange-18.0.1.1.1.dist-info/WHEEL
odoo_addon_server_action_mass_edit_onchange-18.0.1.1.1.dist-info/top_level.txt
odoo_addon_server_action_mass_edit_onchange-18.0.1.1.1.dist-info/RECORD
