Metadata-Version: 2.1
Name: odoo-addon-server_action_mass_edit_onchange
Version: 18.0.1.1.1
Requires-Python: >=3.10
Requires-Dist: odoo-addon-onchange_helper==18.0.*
Requires-Dist: odoo-addon-server_action_mass_edit==18.0.*
Requires-Dist: odoo==18.0.*
Summary: Extension of server_action_mass_edit
Home-page: https://github.com/OCA/server-ux
License: AGPL-3
Author: Camptocamp, Odoo Community Association (OCA)
Author-email: support@odoo-community.org
Classifier: Programming Language :: Python
Classifier: Framework :: Odoo
Classifier: Framework :: Odoo :: 18.0
Classifier: License :: OSI Approved :: GNU Affero General Public License v3
